lolite/__init__.py
lolite/__main__.py
lolite/lib/__init__.py
lolite/lib/deployer.py
lolite/lib/hook_orchestrator.py
lolite/lib/logger.py
lolite/lib/orchestrator.py
lolite/lib/subproc.py
lolite/lib/subscription.py
lolite/lib/hooks/BashScript.py
lolite/lib/hooks/Python3Script.py
lolite/lib/hooks/PythonScript.py
lolite/lib/hooks/__init__.py
lolite/lib/hooks/hook_base.py
lolite-0.0.3.dist-info/LICENSE
lolite-0.0.3.dist-info/METADATA
lolite-0.0.3.dist-info/WHEEL
lolite-0.0.3.dist-info/entry_points.txt
lolite-0.0.3.dist-info/top_level.txt
lolite-0.0.3.dist-info/RECORD
