Metadata-Version: 2.1
Name: lolite
Version: 0.0.3
Summary: Azure Bicep Deployment Orchestration
Home-page: https://github.com/NathanKewley/lolite
Author: Nathan Kewley
Author-email: nathan.kewley@gmail.com
License: UNKNOWN
Project-URL: Bug Tracker, https://github.com/NathanKewley/lolite/issues
Platform: UNKNOWN
Classifier: Programming Language :: Python :: 3
Classifier: Operating System :: OS Independent
Requires-Python: >=3.6
License-File: LICENSE
